exercises/e8_waveforms/f.v
module f(
    input logic[4:0] a, input logic[4:0] b,
    output logic[2:0] x, output logic[2:0] y
);

    assign x = a[2:0] + b[2:0];
    assign y = a[4:2] + b[4:2];

endmodule

exercises/e8_waveforms/e8_waveforms.v
module e8_waveforms();

    logic[4:0] a, b;
    logic[2:0] x, y;

    integer i;
    integer ii;

    f func(.a(a), .b(b), .x(x), .y(y));

    initial begin
        $dumpfile("e8_waveforms.vcd");
        $dumpvars(0, e8_waveforms);
        #1;
        for(i = 0; i < 6'b100000; i++) begin
            a = i;
            for(ii = 0; ii < 6'b100000; ii++) begin
                b = ii;
                #1;
            end
        end   
        $finish();
    end

endmodule

exercises/e8_waveforms/e8_waveforms.vcd
$date
	Wed Nov 10 17:51:56 2021
$end
$version
	Icarus Verilog
$end
$timescale
	1s
$end
$scope module e8_waveforms $end
$var wire 3 ! y [2:0] $end
$var wire 3 " x [2:0] $end
$var reg 5 # a [4:0] $end
$var reg 5 $ b [4:0] $end
$var integer 32 % i [31:0] $end
$var integer 32 & ii [31:0] $end
$scope module func $end
$var wire 5 ' a [4:0] $end
$var wire 5 ( b [4:0] $end
$var wire 3 ) y [2:0] $end
$var wire 3 * x [2:0] $end
$upscope $end
$upscope $end
$enddefinitions $end
#0
$dumpvars
bx *
bx )
bx (
bx '
bx &
bx %
bx $
bx #
bx "
bx !
$end
#1
b0 "
b0 *
b0 !
b0 )
b0 $
b0 (
b0 &
b0 #
b0 '
b0 %
#2
b1 "
b1 *
b1 $
b1 (
b1 &
#3
b10 "
b10 *
b10 $
b10 (
b10 &
#4
b11 "
b11 *
b11 $
b11 (
b11 &
#5
b100 "
b100 *
b1 !
b1 )
b100 $
b100 (
b100 &
#6
b101 "
b101 *
b101 $
b101 (
b101 &
#7
b110 "
b110 *
b110 $
b110 (
b110 &
#8
b111 "
b111 *
b111 $
b111 (
b111 &
#9
b0 "
b0 *
b10 !
b10 )
b1000 $
b1000 (
b1000 &
#10
b1 "
b1 *
b1001 $
b1001 (
b1001 &
#11
b10 "
b10 *
b1010 $
b1010 (
b1010 &
#12
b11 "
b11 *
b1011 $
b1011 (
b1011 &
#13
b100 "
b100 *
b11 !
b11 )
b1100 $
b1100 (
b1100 &
#14
b101 "
b101 *
b1101 $
b1101 (
b1101 &
#15
b110 "
b110 *
b1110 $
b1110 (
b1110 &
#16
b111 "
b111 *
b1111 $
b1111 (
b1111 &
#17
b0 "
b0 *
b100 !
b100 )
b10000 $
b10000 (
b10000 &
#18
b1 "
b1 *
b10001 $
b10001 (
b10001 &
#19
b10 "
b10 *
b10010 $
b10010 (
b10010 &
#20
b11 "
b11 *
b10011 $
b10011 (
b10011 &
#21
b100 "
b100 *
b101 !
b101 )
b10100 $
b10100 (
b10100 &
#22
b101 "
b101 *
b10101 $
b10101 (
b10101 &
#23
b110 "
b110 *
b10110 $
b10110 (
b10110 &
#24
b111 "
b111 *
b10111 $
b10111 (
b10111 &
#25
b0 "
b0 *
b110 !
b110 )
b11000 $
b11000 (
b11000 &
#26
b1 "
b1 *
b11001 $
b11001 (
b11001 &
#27
b10 "
b10 *
b11010 $
b11010 (
b11010 &
#28
b11 "
b11 *
b11011 $
b11011 (
b11011 &
#29
b100 "
b100 *
b111 !
b111 )
b11100 $
b11100 (
b11100 &
#30
b101 "
b101 *
b11101 $
b11101 (
b11101 &
#31
b110 "
b110 *
b11110 $
b11110 (
b11110 &
#32
b111 "
b111 *
b11111 $
b11111 (
b11111 &
#33
b0 !
b0 )
b1 "
b1 *
b0 $
b0 (
b1 #
b1 '
b1 %
b0 &
#34
b10 "
b10 *
b1 $
b1 (
b1 &
#35
b11 "
b11 *
b10 $
b10 (
b10 &
#36
b100 "
b100 *
b11 $
b11 (
b11 &
#37
b101 "
b101 *
b1 !
b1 )
b100 $
b100 (
b100 &
#38
b110 "
b110 *
b101 $
b101 (
b101 &
#39
b111 "
b111 *
b110 $
b110 (
b110 &
#40
b0 "
b0 *
b111 $
b111 (
b111 &
#41
b1 "
b1 *
b10 !
b10 )
b1000 $
b1000 (
b1000 &
#42
b10 "
b10 *
b1001 $
b1001 (
b1001 &
#43
b11 "
b11 *
b1010 $
b1010 (
b1010 &
#44
b100 "
b100 *
b1011 $
b1011 (
b1011 &
#45
b101 "
b101 *
b11 !
b11 )
b1100 $
b1100 (
b1100 &
#46
b110 "
b110 *
b1101 $
b1101 (
b1101 &
#47
b111 "
b111 *
b1110 $
b1110 (
b1110 &
#48
b0 "
b0 *
b1111 $
b1111 (
b1111 &
#49
b1 "
b1 *
b100 !
b100 )
b10000 $
b10000 (
b10000 &
#50
b10 "
b10 *
b10001 $
b10001 (
b10001 &
#51
b11 "
b11 *
b10010 $
b10010 (
b10010 &
#52
b100 "
b100 *
b10011 $
b10011 (
b10011 &
#53
b101 "
b101 *
b101 !
b101 )
b10100 $
b10100 (
b10100 &
#54
b110 "
b110 *
b10101 $
b10101 (
b10101 &
#55
b111 "
b111 *
b10110 $
b10110 (
b10110 &
#56
b0 "
b0 *
b10111 $
b10111 (
b10111 &
#57
b1 "
b1 *
b110 !
b110 )
b11000 $
b11000 (
b11000 &
#58
b10 "
b10 *
b11001 $
b11001 (
b11001 &
#59
b11 "
b11 *
b11010 $
b11010 (
b11010 &
#60
b100 "
b100 *
b11011 $
b11011 (
b11011 &
#61
b101 "
b101 *
b111 !
b111 )
b11100 $
b11100 (
b11100 &
#62
b110 "
b110 *
b11101 $
b11101 (
b11101 &
#63
b111 "
b111 *
b11110 $
b11110 (
b11110 &
#64
b0 "
b0 *
b11111 $
b11111 (
b11111 &
#65
b0 !
b0 )
b10 "
b10 *
b0 $
b0 (
b10 #
b10 '
b10 %
b0 &
#66
b11 "
b11 *
b1 $
b1 (
b1 &
#67
b100 "
b100 *
b10 $
b10 (
b10 &
#68
b101 "
b101 *
b11 $
b11 (
b11 &
#69
b110 "
b110 *
b1 !
b1 )
b100 $
b100 (
b100 &
#70
b111 "
b111 *
b101 $
b101 (
b101 &
#71
b0 "
b0 *
b110 $
b110 (
b110 &
#72
b1 "
b1 *
b111 $
b111 (
b111 &
#73
b10 "
b10 *
b10 !
b10 )
b1000 $
b1000 (
b1000 &
#74
b11 "
b11 *
b1001 $
b1001 (
b1001 &
#75
b100 "
b100 *
b1010 $
b1010 (
b1010 &
#76
b101 "
b101 *
b1011 $
b1011 (
b1011 &
#77
b110 "
b110 *
b11 !
b11 )
b1100 $
b1100 (
b1100 &
#78
b111 "
b111 *
b1101 $
b1101 (
b1101 &
#79
b0 "
b0 *
b1110 $
b1110 (
b1110 &
#80
b1 "
b1 *
b1111 $
b1111 (
b1111 &
#81
b10 "
b10 *
b100 !
b100 )
b10000 $
b10000 (
b10000 &
#82
b11 "
b11 *
b10001 $
b10001 (
b10001 &
#83
b100 "
b100 *
b10010 $
b10010 (
b10010 &
#84
b101 "
b101 *
b10011 $
b10011 (
b10011 &
#85
b110 "
b110 *
b101 !
b101 )
b10100 $
b10100 (
b10100 &
#86
b111 "
b111 *
b10101 $
b10101 (
b10101 &
#87
b0 "
b0 *
b10110 $
b10110 (
b10110 &
#88
b1 "
b1 *
b10111 $
b10111 (
b10111 &
#89
b10 "
b10 *
b110 !
b110 )
b11000 $
b11000 (
b11000 &
#90
b11 "
b11 *
b11001 $
b11001 (
b11001 &
#91
b100 "
b100 *
b11010 $
b11010 (
b11010 &
#92
b101 "
b101 *
b11011 $
b11011 (
b11011 &
#93
b110 "
b110 *
b111 !
b111 )
b11100 $
b11100 (
b11100 &
#94
b111 "
b111 *
b11101 $
b11101 (
b11101 &
#95
b0 "
b0 *
b11110 $
b11110 (
b11110 &
#96
b1 "
b1 *
b11111 $
b11111 (
b11111 &
#97
b0 !
b0 )
b11 "
b11 *
b0 $
b0 (
b11 #
b11 '
b11 %
b0 &
#98
b100 "
b100 *
b1 $
b1 (
b1 &
#99
b101 "
b101 *
b10 $
b10 (
b10 &
#100
b110 "
b110 *
b11 $
b11 (
b11 &
#101
b111 "
b111 *
b1 !
b1 )
b100 $
b100 (
b100 &
#102
b0 "
b0 *
b101 $
b101 (
b101 &
#103
b1 "
b1 *
b110 $
b110 (
b110 &
#104
b10 "
b10 *
b111 $
b111 (
b111 &
#105
b11 "
b11 *
b10 !
b10 )
b1000 $
b1000 (
b1000 &
#106
b100 "
b100 *
b1001 $
b1001 (
b1001 &
#107
b101 "
b101 *
b1010 $
b1010 (
b1010 &
#108
b110 "
b110 *
b1011 $
b1011 (
b1011 &
#109
b111 "
b111 *
b11 !
b11 )
b1100 $
b1100 (
b1100 &
#110
b0 "
b0 *
b1101 $
b1101 (
b1101 &
#111
b1 "
b1 *
b1110 $
b1110 (
b1110 &
#112
b10 "
b10 *
b1111 $
b1111 (
b1111 &
#113
b11 "
b11 *
b100 !
b100 )
b10000 $
b10000 (
b10000 &
#114
b100 "
b100 *
b10001 $
b10001 (
b10001 &
#115
b101 "
b101 *
b10010 $
b10010 (
b10010 &
#116
b110 "
b110 *
b10011 $
b10011 (
b10011 &
#117
b111 "
b111 *
b101 !
b101 )
b10100 $
b10100 (
b10100 &
#118
b0 "
b0 *
b10101 $
b10101 (
b10101 &
#119
b1 "
b1 *
b10110 $
b10110 (
b10110 &
#120
b10 "
b10 *
b10111 $
b10111 (
b10111 &
#121
b11 "
b11 *
b110 !
b110 )
b11000 $
b11000 (
b11000 &
#122
b100 "
b100 *
b11001 $
b11001 (
b11001 &
#123
b101 "
b101 *
b11010 $
b11010 (
b11010 &
#124
b110 "
b110 *
b11011 $
b11011 (
b11011 &
#125
b111 "
b111 *
b111 !
b111 )
b11100 $
b11100 (
b11100 &
#126
b0 "
b0 *
b11101 $
b11101 (
b11101 &
#127
b1 "
b1 *
b11110 $
b11110 (
b11110 &
#128
b10 "
b10 *
b11111 $
b11111 (
b11111 &
#129
b100 "
b100 *
b1 !
b1 )
b0 $
b0 (
b100 #
b100 '
b100 %
b0 &
#130
b101 "
b101 *
b1 $
b1 (
b1 &
#131
b110 "
b110 *
b10 $
b10 (
b10 &
#132
b111 "
b111 *
b11 $
b11 (
b11 &
#133
b0 "
b0 *
b10 !
b10 )
b100 $
b100 (
b100 &
#134
b1 "
b1 *
b101 $
b101 (
b101 &
#135
b10 "
b10 *
b110 $
b110 (
b110 &
#136
b11 "
b11 *
b111 $
b111 (
b111 &
#137
b100 "
b100 *
b11 !
b11 )
b1000 $
b1000 (
b1000 &
#138
b101 "
b101 *
b1001 $
b1001 (
b1001 &
#139
b110 "
b110 *
b1010 $
b1010 (
b1010 &
#140
b111 "
b111 *
b1011 $
b1011 (
b1011 &
#141
b0 "
b0 *
b100 !
b100 )
b1100 $
b1100 (
b1100 &
#142
b1 "
b1 *
b1101 $
b1101 (
b1101 &
#143
b10 "
b10 *
b1110 $
b1110 (
b1110 &
#144
b11 "
b11 *
b1111 $
b1111 (
b1111 &
#145
b100 "
b100 *
b101 !
b101 )
b10000 $
b10000 (
b10000 &
#146
b101 "
b101 *
b10001 $
b10001 (
b10001 &
#147
b110 "
b110 *
b10010 $
b10010 (
b10010 &
#148
b111 "
b111 *
b10011 $
b10011 (
b10011 &
#149
b0 "
b0 *
b110 !
b110 )
b10100 $
b10100 (
b10100 &
#150
b1 "
b1 *
b10101 $
b10101 (
b10101 &
#151
b10 "
b10 *
b10110 $
b10110 (
b10110 &
#152
b11 "
b11 *
b10111 $
b10111 (
b10111 &
#153
b100 "
b100 *
b111 !
b111 )
b11000 $
b11000 (
b11000 &
#154
b101 "
b101 *
b11001 $
b11001 (
b11001 &
#155
b110 "
b110 *
b11010 $
b11010 (
b11010 &
#156
b111 "
b111 *
b11011 $
b11011 (
b11011 &
#157
b0 "
b0 *
b0 !
b0 )
b11100 $
b11100 (
b11100 &
#158
b1 "
b1 *
b11101 $
b11101 (
b11101 &
#159
b10 "
b10 *
b11110 $
b11110 (
b11110 &
#160
b11 "
b11 *
b11111 $
b11111 (
b11111 &
#161
b1 !
b1 )
b101 "
b101 *
b0 $
b0 (
b101 #
b101 '
b101 %
b0 &
#162
b110 "
b110 *
b1 $
b1 (
b1 &
#163
b111 "
b111 *
b10 $
b10 (
b10 &
#164
b0 "
b0 *
b11 $
b11 (
b11 &
#165
b1 "
b1 *
b10 !
b10 )
b100 $
b100 (
b100 &
#166
b10 "
b10 *
b101 $
b101 (
b101 &
#167
b11 "
b11 *
b110 $
b110 (
b110 &
#168
b100 "
b100 *
b111 $
b111 (
b111 &
#169
b101 "
b101 *
b11 !
b11 )
b1000 $
b1000 (
b1000 &
#170
b110 "
b110 *
b1001 $
b1001 (
b1001 &
#171
b111 "
b111 *
b1010 $
b1010 (
b1010 &
#172
b0 "
b0 *
b1011 $
b1011 (
b1011 &
#173
b1 "
b1 *
b100 !
b100 )
b1100 $
b1100 (
b1100 &
#174
b10 "
b10 *
b1101 $
b1101 (
b1101 &
#175
b11 "
b11 *
b1110 $
b1110 (
b1110 &
#176
b100 "
b100 *
b1111 $
b1111 (
b1111 &
#177
b101 "
b101 *
b101 !
b101 )
b10000 $
b10000 (
b10000 &
#178
b110 "
b110 *
b10001 $
b10001 (
b10001 &
#179
b111 "
b111 *
b10010 $
b10010 (
b10010 &
#180
b0 "
b0 *
b10011 $
b10011 (
b10011 &
#181
b1 "
b1 *
b110 !
b110 )
b10100 $
b10100 (
b10100 &
#182
b10 "
b10 *
b10101 $
b10101 (
b10101 &
#183
b11 "
b11 *
b10110 $
b10110 (
b10110 &
#184
b100 "
b100 *
b10111 $
b10111 (
b10111 &
#185
b101 "
b101 *
b111 !
b111 )
b11000 $
b11000 (
b11000 &
#186
b110 "
b110 *
b11001 $
b11001 (
b11001 &
#187
b111 "
b111 *
b11010 $
b11010 (
b11010 &
#188
b0 "
b0 *
b11011 $
b11011 (
b11011 &
#189
b1 "
b1 *
b0 !
b0 )
b11100 $
b11100 (
b11100 &
#190
b10 "
b10 *
b11101 $
b11101 (
b11101 &
#191
b11 "
b11 *
b11110 $
b11110 (
b11110 &
#192
b100 "
b100 *
b11111 $
b11111 (
b11111 &
#193
b1 !
b1 )
b110 "
b110 *
b0 $
b0 (
b110 #
b110 '
b110 %
b0 &
#194
b111 "
b111 *
b1 $
b1 (
b1 &
#195
b0 "
b0 *
b10 $
b10 (
b10 &
#196
b1 "
b1 *
b11 $
b11 (
b11 &
#197
b10 "
b10 *
b10 !
b10 )
b100 $
b100 (
b100 &
#198
b11 "
b11 *
b101 $
b101 (
b101 &
#199
b100 "
b100 *
b110 $
b110 (
b110 &
#200
b101 "
b101 *
b111 $
b111 (
b111 &
#201
b110 "
b110 *
b11 !
b11 )
b1000 $
b1000 (
b1000 &
#202
b111 "
b111 *
b1001 $
b1001 (
b1001 &
#203
b0 "
b0 *
b1010 $
b1010 (
b1010 &
#204
b1 "
b1 *
b1011 $
b1011 (
b1011 &
#205
b10 "
b10 *
b100 !
b100 )
b1100 $
b1100 (
b1100 &
#206
b11 "
b11 *
b1101 $
b1101 (
b1101 &
#207
b100 "
b100 *
b1110 $
b1110 (
b1110 &
#208
b101 "
b101 *
b1111 $
b1111 (
b1111 &
#209
b110 "
b110 *
b101 !
b101 )
b10000 $
b10000 (
b10000 &
#210
b111 "
b111 *
b10001 $
b10001 (
b10001 &
#211
b0 "
b0 *
b10010 $
b10010 (
b10010 &
#212
b1 "
b1 *
b10011 $
b10011 (
b10011 &
#213
b10 "
b10 *
b110 !
b110 )
b10100 $
b10100 (
b10100 &
#214
b11 "
b11 *
b10101 $
b10101 (
b10101 &
#215
b100 "
b100 *
b10110 $
b10110 (
b10110 &
#216
b101 "
b101 *
b10111 $
b10111 (
b10111 &
#217
b110 "
b110 *
b111 !
b111 )
b11000 $
b11000 (
b11000 &
#218
b111 "
b111 *
b11001 $
b11001 (
b11001 &
#219
b0 "
b0 *
b11010 $
b11010 (
b11010 &
#220
b1 "
b1 *
b11011 $
b11011 (
b11011 &
#221
b10 "
b10 *
b0 !
b0 )
b11100 $
b11100 (
b11100 &
#222
b11 "
b11 *
b11101 $
b11101 (
b11101 &
#223
b100 "
b100 *
b11110 $
b11110 (
b11110 &
#224
b101 "
b101 *
b11111 $
b11111 (
b11111 &
#225
b1 !
b1 )
b111 "
b111 *
b0 $
b0 (
b111 #
b111 '
b111 %
b0 &
#226
b0 "
b0 *
b1 $
b1 (
b1 &
#227
b1 "
b1 *
b10 $
b10 (
b10 &
#228
b10 "
b10 *
b11 $
b11 (
b11 &
#229
b11 "
b11 *
b10 !
b10 )
b100 $
b100 (
b100 &
#230
b100 "
b100 *
b101 $
b101 (
b101 &
#231
b101 "
b101 *
b110 $
b110 (
b110 &
#232
b110 "
b110 *
b111 $
b111 (
b111 &
#233
b111 "
b111 *
b11 !
b11 )
b1000 $
b1000 (
b1000 &
#234
b0 "
b0 *
b1001 $
b1001 (
b1001 &
#235
b1 "
b1 *
b1010 $
b1010 (
b1010 &
#236
b10 "
b10 *
b1011 $
b1011 (
b1011 &
#237
b11 "
b11 *
b100 !
b100 )
b1100 $
b1100 (
b1100 &
#238
b100 "
b100 *
b1101 $
b1101 (
b1101 &
#239
b101 "
b101 *
b1110 $
b1110 (
b1110 &
#240
b110 "
b110 *
b1111 $
b1111 (
b1111 &
#241
b111 "
b111 *
b101 !
b101 )
b10000 $
b10000 (
b10000 &
#242
b0 "
b0 *
b10001 $
b10001 (
b10001 &
#243
b1 "
b1 *
b10010 $
b10010 (
b10010 &
#244
b10 "
b10 *
b10011 $
b10011 (
b10011 &
#245
b11 "
b11 *
b110 !
b110 )
b10100 $
b10100 (
b10100 &
#246
b100 "
b100 *
b10101 $
b10101 (
b10101 &
#247
b101 "
b101 *
b10110 $
b10110 (
b10110 &
#248
b110 "
b110 *
b10111 $
b10111 (
b10111 &
#249
b111 "
b111 *
b111 !
b111 )
b11000 $
b11000 (
b11000 &
#250
b0 "
b0 *
b11001 $
b11001 (
b11001 &
#251
b1 "
b1 *
b11010 $
b11010 (
b11010 &
#252
b10 "
b10 *
b11011 $
b11011 (
b11011 &
#253
b11 "
b11 *
b0 !
b0 )
b11100 $
b11100 (
b11100 &
#254
b100 "
b100 *
b11101 $
b11101 (
b11101 &
#255
b101 "
b101 *
b11110 $
b11110 (
b11110 &
#256
b110 "
b110 *
b11111 $
b11111 (
b11111 &
#257
b0 "
b0 *
b10 !
b10 )
b0 $
b0 (
b1000 #
b1000 '
b1000 %
b0 &
#258
b1 "
b1 *
b1 $
b1 (
b1 &
#259
b10 "
b10 *
b10 $
b10 (
b10 &
#260
b11 "
b11 *
b11 $
b11 (
b11 &
#261
b100 "
b100 *
b11 !
b11 )
b100 $
b100 (
b100 &
#262
b101 "
b101 *
b101 $
b101 (
b101 &
#263
b110 "
b110 *
b110 $
b110 (
b110 &
#264
b111 "
b111 *
b111 $
b111 (
b111 &
#265
b0 "
b0 *
b100 !
b100 )
b1000 $
b1000 (
b1000 &
#266
b1 "
b1 *
b1001 $
b1001 (
b1001 &
#267
b10 "
b10 *
b1010 $
b1010 (
b1010 &
#268
b11 "
b11 *
b1011 $
b1011 (
b1011 &
#269
b100 "
b100 *
b101 !
b101 )
b1100 $
b1100 (
b1100 &
#270
b101 "
b101 *
b1101 $
b1101 (
b1101 &
#271
b110 "
b110 *
b1110 $
b1110 (
b1110 &
#272
b111 "
b111 *
b1111 $
b1111 (
b1111 &
#273
b0 "
b0 *
b110 !
b110 )
b10000 $
b10000 (
b10000 &
#274
b1 "
b1 *
b10001 $
b10001 (
b10001 &
#275
b10 "
b10 *
b10010 $
b10010 (
b10010 &
#276
b11 "
b11 *
b10011 $
b10011 (
b10011 &
#277
b100 "
b100 *
b111 !
b111 )
b10100 $
b10100 (
b10100 &
#278
b101 "
b101 *
b10101 $
b10101 (
b10101 &
#279
b110 "
b110 *
b10110 $
b10110 (
b10110 &
#280
b111 "
b111 *
b10111 $
b10111 (
b10111 &
#281
b0 "
b0 *
b0 !
b0 )
b11000 $
b11000 (
b11000 &
#282
b1 "
b1 *
b11001 $
b11001 (
b11001 &
#283
b10 "
b10 *
b11010 $
b11010 (
b11010 &
#284
b11 "
b11 *
b11011 $
b11011 (
b11011 &
#285
b100 "
b100 *
b1 !
b1 )
b11100 $
b11100 (
b11100 &
#286
b101 "
b101 *
b11101 $
b11101 (
b11101 &
#287
b110 "
b110 *
b11110 $
b11110 (
b11110 &
#288
b111 "
b111 *
b11111 $
b11111 (
b11111 &
#289
b10 !
b10 )
b1 "
b1 *
b0 $
b0 (
b1001 #
b1001 '
b1001 %
b0 &
#290
b10 "
b10 *
b1 $
b1 (
b1 &
#291
b11 "
b11 *
b10 $
b10 (
b10 &
#292
b100 "
b100 *
b11 $
b11 (
b11 &
#293
b101 "
b101 *
b11 !
b11 )
b100 $
b100 (
b100 &
#294
b110 "
b110 *
b101 $
b101 (
b101 &
#295
b111 "
b111 *
b110 $
b110 (
b110 &
#296
b0 "
b0 *
b111 $
b111 (
b111 &
#297
b1 "
b1 *
b100 !
b100 )
b1000 $
b1000 (
b1000 &
#298
b10 "
b10 *
b1001 $
b1001 (
b1001 &
#299
b11 "
b11 *
b1010 $
b1010 (
b1010 &
#300
b100 "
b100 *
b1011 $
b1011 (
b1011 &
#301
b101 "
b101 *
b101 !
b101 )
b1100 $
b1100 (
b1100 &
#302
b110 "
b110 *
b1101 $
b1101 (
b1101 &
#303
b111 "
b111 *
b1110 $
b1110 (
b1110 &
#304
b0 "
b0 *
b1111 $
b1111 (
b1111 &
#305
b1 "
b1 *
b110 !
b110 )
b10000 $
b10000 (
b10000 &
#306
b10 "
b10 *
b10001 $
b10001 (
b10001 &
#307
b11 "
b11 *
b10010 $
b10010 (
b10010 &
#308
b100 "
b100 *
b10011 $
b10011 (
b10011 &
#309
b101 "
b101 *
b111 !
b111 )
b10100 $
b10100 (
b10100 &
#310
b110 "
b110 *
b10101 $
b10101 (
b10101 &
#311
b111 "
b111 *
b10110 $
b10110 (
b10110 &
#312
b0 "
b0 *
b10111 $
b10111 (
b10111 &
#313
b1 "
b1 *
b0 !
b0 )
b11000 $
b11000 (
b11000 &
#314
b10 "
b10 *
b11001 $
b11001 (
b11001 &
#315
b11 "
b11 *
b11010 $
b11010 (
b11010 &
#316
b100 "
b100 *
b11011 $
b11011 (
b11011 &
#317
b101 "
b101 *
b1 !
b1 )
b11100 $
b11100 (
b11100 &
#318
b110 "
b110 *
b11101 $
b11101 (
b11101 &
#319
b111 "
b111 *
b11110 $
b11110 (
b11110 &
#320
b0 "
b0 *
b11111 $
b11111 (
b11111 &
#321
b10 !
b10 )
b10 "
b10 *
b0 $
b0 (
b1010 #
b1010 '
b1010 %
b0 &
#322
b11 "
b11 *
b1 $
b1 (
b1 &
#323
b100 "
b100 *
b10 $
b10 (
b10 &
#324
b101 "
b101 *
b11 $
b11 (
b11 &
#325
b110 "
b110 *
b11 !
b11 )
b100 $
b100 (
b100 &
#326
b111 "
b111 *
b101 $
b101 (
b101 &
#327
b0 "
b0 *
b110 $
b110 (
b110 &
#328
b1 "
b1 *
b111 $
b111 (
b111 &
#329
b10 "
b10 *
b100 !
b100 )
b1000 $
b1000 (
b1000 &
#330
b11 "
b11 *
b1001 $
b1001 (
b1001 &
#331
b100 "
b100 *
b1010 $
b1010 (
b1010 &
#332
b101 "
b101 *
b1011 $
b1011 (
b1011 &
#333
b110 "
b110 *
b101 !
b101 )
b1100 $
b1100 (
b1100 &
#334
b111 "
b111 *
b1101 $
b1101 (
b1101 &
#335
b0 "
b0 *
b1110 $
b1110 (
b1110 &
#336
b1 "
b1 *
b1111 $
b1111 (
b1111 &
#337
b10 "
b10 *
b110 !
b110 )
b10000 $
b10000 (
b10000 &
#338
b11 "
b11 *
b10001 $
b10001 (
b10001 &
#339
b100 "
b100 *
b10010 $
b10010 (
b10010 &
#340
b101 "
b101 *
b10011 $
b10011 (
b10011 &
#341
b110 "
b110 *
b111 !
b111 )
b10100 $
b10100 (
b10100 &
#342
b111 "
b111 *
b10101 $
b10101 (
b10101 &
#343
b0 "
b0 *
b10110 $
b10110 (
b10110 &
#344
b1 "
b1 *
b10111 $
b10111 (
b10111 &
#345
b10 "
b10 *
b0 !
b0 )
b11000 $
b11000 (
b11000 &
#346
b11 "
b11 *
b11001 $
b11001 (
b11001 &
#347
b100 "
b100 *
b11010 $
b11010 (
b11010 &
#348
b101 "
b101 *
b11011 $
b11011 (
b11011 &
#349
b110 "
b110 *
b1 !
b1 )
b11100 $
b11100 (
b11100 &
#350
b111 "
b111 *
b11101 $
b11101 (
b11101 &
#351
b0 "
b0 *
b11110 $
b11110 (
b11110 &
#352
b1 "
b1 *
b11111 $
b11111 (
b11111 &
#353
b10 !
b10 )
b11 "
b11 *
b0 $
b0 (
b1011 #
b1011 '
b1011 %
b0 &
#354
b100 "
b100 *
b1 $
b1 (
b1 &
#355
b101 "
b101 *
b10 $
b10 (
b10 &
#356
b110 "
b110 *
b11 $
b11 (
b11 &
#357
b111 "
b111 *
b11 !
b11 )
b100 $
b100 (
b100 &
#358
b0 "
b0 *
b101 $
b101 (
b101 &
#359
b1 "
b1 *
b110 $
b110 (
b110 &
#360
b10 "
b10 *
b111 $
b111 (
b111 &
#361
b11 "
b11 *
b100 !
b100 )
b1000 $
b1000 (
b1000 &
#362
b100 "
b100 *
b1001 $
b1001 (
b1001 &
#363
b101 "
b101 *
b1010 $
b1010 (
b1010 &
#364
b110 "
b110 *
b1011 $
b1011 (
b1011 &
#365
b111 "
b111 *
b101 !
b101 )
b1100 $
b1100 (
b1100 &
#366
b0 "
b0 *
b1101 $
b1101 (
b1101 &
#367
b1 "
b1 *
b1110 $
b1110 (
b1110 &
#368
b10 "
b10 *
b1111 $
b1111 (
b1111 &
#369
b11 "
b11 *
b110 !
b110 )
b10000 $
b10000 (
b10000 &
#370
b100 "
b100 *
b10001 $
b10001 (
b10001 &
#371
b101 "
b101 *
b10010 $
b10010 (
b10010 &
#372
b110 "
b110 *
b10011 $
b10011 (
b10011 &
#373
b111 "
b111 *
b111 !
b111 )
b10100 $
b10100 (
b10100 &
#374
b0 "
b0 *
b10101 $
b10101 (
b10101 &
#375
b1 "
b1 *
b10110 $
b10110 (
b10110 &
#376
b10 "
b10 *
b10111 $
b10111 (
b10111 &
#377
b11 "
b11 *
b0 !
b0 )
b11000 $
b11000 (
b11000 &
#378
b100 "
b100 *
b11001 $
b11001 (
b11001 &
#379
b101 "
b101 *
b11010 $
b11010 (
b11010 &
#380
b110 "
b110 *
b11011 $
b11011 (
b11011 &
#381
b111 "
b111 *
b1 !
b1 )
b11100 $
b11100 (
b11100 &
#382
b0 "
b0 *
b11101 $
b11101 (
b11101 &
#383
b1 "
b1 *
b11110 $
b11110 (
b11110 &
#384
b10 "
b10 *
b11111 $
b11111 (
b11111 &
#385
b100 "
b100 *
b11 !
b11 )
b0 $
b0 (
b1100 #
b1100 '
b1100 %
b0 &
#386
b101 "
b101 *
b1 $
b1 (
b1 &
#387
b110 "
b110 *
b10 $
b10 (
b10 &
#388
b111 "
b111 *
b11 $
b11 (
b11 &
#389
b0 "
b0 *
b100 !
b100 )
b100 $
b100 (
b100 &
#390
b1 "
b1 *
b101 $
b101 (
b101 &
#391
b10 "
b10 *
b110 $
b110 (
b110 &
#392
b11 "
b11 *
b111 $
b111 (
b111 &
#393
b100 "
b100 *
b101 !
b101 )
b1000 $
b1000 (
b1000 &
#394
b101 "
b101 *
b1001 $
b1001 (
b1001 &
#395
b110 "
b110 *
b1010 $
b1010 (
b1010 &
#396
b111 "
b111 *
b1011 $
b1011 (
b1011 &
#397
b0 "
b0 *
b110 !
b110 )
b1100 $
b1100 (
b1100 &
#398
b1 "
b1 *
b1101 $
b1101 (
b1101 &
#399
b10 "
b10 *
b1110 $
b1110 (
b1110 &
#400
b11 "
b11 *
b1111 $
b1111 (
b1111 &
#401
b100 "
b100 *
b111 !
b111 )
b10000 $
b10000 (
b10000 &
#402
b101 "
b101 *
b10001 $
b10001 (
b10001 &
#403
b110 "
b110 *
b10010 $
b10010 (
b10010 &
#404
b111 "
b111 *
b10011 $
b10011 (
b10011 &
#405
b0 "
b0 *
b0 !
b0 )
b10100 $
b10100 (
b10100 &
#406
b1 "
b1 *
b10101 $
b10101 (
b10101 &
#407
b10 "
b10 *
b10110 $
b10110 (
b10110 &
#408
b11 "
b11 *
b10111 $
b10111 (
b10111 &
#409
b100 "
b100 *
b1 !
b1 )
b11000 $
b11000 (
b11000 &
#410
b101 "
b101 *
b11001 $
b11001 (
b11001 &
#411
b110 "
b110 *
b11010 $
b11010 (
b11010 &
#412
b111 "
b111 *
b11011 $
b11011 (
b11011 &
#413
b0 "
b0 *
b10 !
b10 )
b11100 $
b11100 (
b11100 &
#414
b1 "
b1 *
b11101 $
b11101 (
b11101 &
#415
b10 "
b10 *
b11110 $
b11110 (
b11110 &
#416
b11 "
b11 *
b11111 $
b11111 (
b11111 &
#417
b11 !
b11 )
b101 "
b101 *
b0 $
b0 (
b1101 #
b1101 '
b1101 %
b0 &
#418
b110 "
b110 *
b1 $
b1 (
b1 &
#419
b111 "
b111 *
b10 $
b10 (
b10 &
#420
b0 "
b0 *
b11 $
b11 (
b11 &
#421
b1 "
b1 *
b100 !
b100 )
b100 $
b100 (
b100 &
#422
b10 "
b10 *
b101 $
b101 (
b101 &
#423
b11 "
b11 *
b110 $
b110 (
b110 &
#424
b100 "
b100 *
b111 $
b111 (
b111 &
#425
b101 "
b101 *
b101 !
b101 )
b1000 $
b1000 (
b1000 &
#426
b110 "
b110 *
b1001 $
b1001 (
b1001 &
#427
b111 "
b111 *
b1010 $
b1010 (
b1010 &
#428
b0 "
b0 *
b1011 $
b1011 (
b1011 &
#429
b1 "
b1 *
b110 !
b110 )
b1100 $
b1100 (
b1100 &
#430
b10 "
b10 *
b1101 $
b1101 (
b1101 &
