exercises/e7_rewriting/multiplier.v

module multiplier(
    input clk,
    input logic valid_in,
    input logic[31:0] a,
    input logic[31:0] b,
    output logic valid_out,
    output logic[63:0] r
);
    logic[31:0] mp, mp_next;
    logic[63:0] mc, mc_next;
    logic[63:0] acc, acc_next;
    logic[5:0] i, i_next;

    logic[3:0] mp_nibble;

    assign mp_nibble = mp[3:0];

    always_comb begin

        case(valid_in)
            1'd1: begin
                mp_next = a;
                mc_next = b;
                acc_next = 0;
                i_next = 0;
            end
            default: begin
                case(i)
                    5'd8: begin end
                    default: begin
                        acc_next = acc + mp_nibble * mc;
                        mp_next = mp>>4;
                        mc_next = mc<<4;
                        case(mp)
                            31'd0: i_next = 8;
                            default: i_next = i + 1;
                        endcase                        
                    end
                endcase
            end
        endcase
    end

    always_ff  @(posedge clk) begin
        mp <= mp_next;
        mc <= mc_next;
        acc <= acc_next;
        i <= i_next;

        case(i_next)
            5'd8: begin
                r <= acc_next;
                valid_out <= 1;                
            end
            default: begin
                r <= r;
                valid_out <= 0;                
            end
        endcase
    end
endmodule

exercises/e7_rewriting/multiplier_tb.v



module multiplier_tb(
);
    logic clk;
    logic[31:0] a, b;
    logic[63:0] r;
    logic valid_in, valid_out;

    initial begin
        $dumpfile("multiplier.vcd");
        $dumpvars(0, multiplier_tb);
        clk = 0;

        #5;

        repeat (100000) begin
            #10 clk = !clk;
        end

        $fatal(2, "Fail : test-bench timed out without positive exit.");
    end

    initial begin
        a = 0;
        b = 0;

         repeat (100) begin
            @(posedge clk);
            #1;
            valid_in = 1;

            @(posedge clk);
            #1;
            valid_in = 0;

            while (valid_out==0) begin
                @(posedge clk);
                #1;
            end
            $display("a=%d, b=%d, r=%d,  time=%t", a, b, r, $time);

            a = a+1;
            b = b+1;
        end

        repeat (100) begin
            @(posedge clk);
            #1;
            valid_in = 1;

            @(posedge clk);
            #1;
            valid_in = 0;

            while (valid_out==0) begin
                @(posedge clk);
                #1;
            end
            $display("a=%d, b=%d, r=%d", a, b, r);
            assert(a*b == r) else $fatal(1, "Product is wrong.");

            a = a+32'h23456789;
            b = b+32'h34567891;
        end

        $display("Finished. Total time = %t", $time);
        $finish;
    end

    multiplier m(
        .clk(clk),
        .valid_in(valid_in), .valid_out(valid_out),
        .a(a), .b(b), .r(r)
    );
endmodule

exercises/e7_rewriting/multiplier.vcd
$date
	Wed Nov 10 16:23:56 2021
$end
$version
	Icarus Verilog
$end
$timescale
	1s
$end
$scope module multiplier_tb $end
$var wire 1 ! valid_out $end
$var wire 64 " r [63:0] $end
$var reg 32 # a [31:0] $end
$var reg 32 $ b [31:0] $end
$var reg 1 % clk $end
$var reg 1 & valid_in $end
$scope module m $end
$var wire 32 ' a [31:0] $end
$var wire 32 ( b [31:0] $end
$var wire 1 % clk $end
$var wire 1 & valid_in $end
$var wire 4 ) mp_nibble [3:0] $end
$var reg 64 * acc [63:0] $end
$var reg 64 + acc_next [63:0] $end
$var reg 6 , i [5:0] $end
$var reg 6 - i_next [5:0] $end
$var reg 64 . mc [63:0] $end
$var reg 64 / mc_next [63:0] $end
$var reg 32 0 mp [31:0] $end
$var reg 32 1 mp_next [31:0] $end
$var reg 64 2 r [63:0] $end
$var reg 1 ! valid_out $end
$upscope $end
$upscope $end
$enddefinitions $end
#0
$dumpvars
bx 2
b0xxxxxxxxxxxxxxxxxxxxxxxxxxxx 1
bx 0
bx0000 /
bx .
bx -
bx ,
bx +
bx *
bx )
b0 (
b0 '
x&
0%
b0 $
b0 #
bx "
x!
$end
#15
bx00000000 /
b0xxxxxxxxxxxxxxxxxxxxxxxx 1
0!
bx0000 .
b0xxxxxxxxxxxxxxxxxxxxxxxxxxxx 0
1%
#16
b0 -
b0 +
b0 /
b0 1
1&
#25
0%
#35
b0 )
b0 ,
b0 *
b0 .
b0 0
1%
#36
b1000 -
0&
#45
0%
#55
1!
b0 "
b0 2
b1000 ,
1%
#56
b1 $
b1 (
b1 #
b1 '
#65
0%
#75
1%
#76
b0 -
b1 /
b1 1
1&
#85
0%
#95
b1 )
0!
b0 ,
b1 .
b1 0
1%
#96
b1 -
b10000 /
b0 1
b1 +
0&
#105
0%
#115
b1000 -
b100000000 /
b0 )
b1 ,
b1 *
b10000 .
b0 0
1%
#125
0%
#135
1!
b1 "
b1 2
b1000 ,
b100000000 .
1%
#136
b10 $
b10 (
b10 #
b10 '
#145
0%
#155
1%
#156
b0 -
b0 +
b10 /
b10 1
1&
#165
0%
#175
b10 )
0!
b0 ,
b0 *
b10 .
b10 0
1%
#176
b1 -
b100000 /
b0 1
b100 +
0&
#185
0%
#195
b1000 -
b1000000000 /
b0 )
b1 ,
b100 *
b100000 .
b0 0
1%
#205
0%
#215
1!
b100 "
b100 2
b1000 ,
b1000000000 .
1%
#216
b11 $
b11 (
b11 #
b11 '
#225
0%
#235
1%
#236
b0 -
b0 +
b11 /
b11 1
1&
#245
0%
#255
b11 )
0!
b0 ,
b0 *
b11 .
b11 0
1%
#256
b1 -
b110000 /
b0 1
b1001 +
0&
#265
0%
#275
b1000 -
b1100000000 /
b0 )
b1 ,
b1001 *
b110000 .
b0 0
1%
#285
0%
#295
1!
b1001 "
b1001 2
b1000 ,
b1100000000 .
1%
#296
b100 $
b100 (
b100 #
b100 '
#305
0%
#315
1%
#316
b0 -
b0 +
b100 /
b100 1
1&
#325
0%
#335
b100 )
0!
b0 ,
b0 *
b100 .
b100 0
1%
#336
b1 -
b1000000 /
b0 1
b10000 +
0&
#345
0%
#355
b1000 -
b10000000000 /
b0 )
b1 ,
b10000 *
b1000000 .
b0 0
1%
#365
0%
#375
1!
b10000 "
b10000 2
b1000 ,
b10000000000 .
1%
#376
b101 $
b101 (
b101 #
b101 '
#385
0%
#395
1%
#396
b0 -
b0 +
b101 /
b101 1
1&
#405
0%
#415
b101 )
0!
b0 ,
b0 *
b101 .
b101 0
1%
#416
b1 -
b1010000 /
b0 1
b11001 +
0&
#425
0%
#435
b1000 -
b10100000000 /
b0 )
b1 ,
b11001 *
b1010000 .
b0 0
1%
#445
0%
#455
1!
b11001 "
b11001 2
b1000 ,
b10100000000 .
1%
#456
b110 $
b110 (
b110 #
b110 '
#465
0%
#475
1%
#476
b0 -
b0 +
b110 /
b110 1
1&
#485
0%
#495
b110 )
0!
b0 ,
b0 *
b110 .
b110 0
1%
#496
b1 -
b1100000 /
b0 1
b100100 +
0&
#505
0%
#515
b1000 -
b11000000000 /
b0 )
b1 ,
b100100 *
b1100000 .
b0 0
1%
#525
0%
#535
1!
b100100 "
b100100 2
b1000 ,
b11000000000 .
1%
#536
b111 $
b111 (
b111 #
b111 '
#545
0%
#555
1%
#556
b0 -
b0 +
b111 /
b111 1
1&
#565
0%
#575
b111 )
0!
b0 ,
b0 *
b111 .
b111 0
1%
#576
b1 -
b1110000 /
b0 1
b110001 +
0&
#585
0%
#595
b1000 -
b11100000000 /
b0 )
b1 ,
b110001 *
b1110000 .
b0 0
1%
#605
0%
#615
1!
b110001 "
b110001 2
b1000 ,
b11100000000 .
1%
#616
b1000 $
b1000 (
b1000 #
b1000 '
#625
0%
#635
1%
#636
b0 -
b0 +
b1000 /
b1000 1
1&
#645
0%
#655
b1000 )
0!
b0 ,
b0 *
b1000 .
b1000 0
1%
#656
b1 -
b10000000 /
b0 1
b1000000 +
0&
#665
0%
#675
b1000 -
b100000000000 /
b0 )
b1 ,
b1000000 *
b10000000 .
b0 0
1%
#685
0%
#695
1!
b1000000 "
b1000000 2
b1000 ,
b100000000000 .
1%
#696
b1001 $
b1001 (
b1001 #
b1001 '
#705
0%
#715
1%
#716
b0 -
b0 +
b1001 /
b1001 1
1&
#725
0%
#735
b1001 )
0!
b0 ,
b0 *
b1001 .
b1001 0
1%
#736
b1 -
b10010000 /
b0 1
b1010001 +
0&
#745
0%
#755
b1000 -
b100100000000 /
b0 )
b1 ,
b1010001 *
b10010000 .
b0 0
1%
#765
0%
#775
1!
b1010001 "
b1010001 2
b1000 ,
b100100000000 .
1%
#776
b1010 $
b1010 (
b1010 #
b1010 '
#785
0%
#795
1%
#796
b0 -
b0 +
b1010 /
b1010 1
1&
#805
0%
#815
b1010 )
0!
b0 ,
b0 *
b1010 .
b1010 0
1%
#816
b1 -
b10100000 /
b0 1
b1100100 +
0&
#825
0%
#835
b1000 -
b101000000000 /
b0 )
b1 ,
b1100100 *
b10100000 .
b0 0
1%
#845
0%
#855
1!
b1100100 "
b1100100 2
b1000 ,
b101000000000 .
1%
#856
b1011 $
b1011 (
b1011 #
b1011 '
#865
0%
#875
1%
#876
b0 -
b0 +
b1011 /
b1011 1
1&
#885
0%
#895
b1011 )
0!
b0 ,
b0 *
b1011 .
b1011 0
1%
#896
b1 -
b10110000 /
b0 1
b1111001 +
0&
#905
0%
#915
b1000 -
b101100000000 /
b0 )
b1 ,
b1111001 *
b10110000 .
b0 0
1%
#925
0%
#935
1!
b1111001 "
b1111001 2
b1000 ,
b101100000000 .
1%
#936
b1100 $
b1100 (
b1100 #
b1100 '
#945
0%
#955
1%
#956
b0 -
b0 +
b1100 /
b1100 1
1&
#965
0%
#975
b1100 )
0!
b0 ,
b0 *
b1100 .
b1100 0
1%
#976
b1 -
b11000000 /
b0 1
b10010000 +
0&
#985
0%
#995
b1000 -
b110000000000 /
b0 )
b1 ,
b10010000 *
b11000000 .
b0 0
1%
#1005
0%
#1015
1!
b10010000 "
b10010000 2
b1000 ,
b110000000000 .
1%
#1016
b1101 $
b1101 (
b1101 #
b1101 '
#1025
0%
#1035
1%
#1036
b0 -
b0 +
b1101 /
b1101 1
1&
#1045
0%
#1055
b1101 )
0!
b0 ,
b0 *
b1101 .
b1101 0
1%
#1056
b1 -
b11010000 /
b0 1
b10101001 +
0&
#1065
0%
#1075
b1000 -
b110100000000 /
b0 )
b1 ,
b10101001 *
b11010000 .
b0 0
1%
#1085
0%
#1095
1!
b10101001 "
b10101001 2
b1000 ,
b110100000000 .
1%
#1096
b1110 $
b1110 (
b1110 #
b1110 '
#1105
0%
#1115
1%
#1116
b0 -
b0 +
b1110 /
b1110 1
1&
#1125
0%
#1135
b1110 )
0!
b0 ,
b0 *
b1110 .
b1110 0
1%
#1136
b1 -
b11100000 /
b0 1
b11000100 +
0&
#1145
0%
#1155
b1000 -
b111000000000 /
b0 )
b1 ,
b11000100 *
b11100000 .
b0 0
1%
#1165
0%
#1175
1!
b11000100 "
b11000100 2
b1000 ,
b111000000000 .
1%
#1176
b1111 $
b1111 (
b1111 #
b1111 '
#1185
0%
#1195
1%
#1196
b0 -
b0 +
b1111 /
b1111 1
1&
#1205
0%
#1215
b1111 )
0!
b0 ,
b0 *
b1111 .
b1111 0
1%
#1216
b1 -
b11110000 /
b0 1
b11100001 +
0&
#1225
0%
#1235
b1000 -
b111100000000 /
b0 )
b1 ,
b11100001 *
b11110000 .
b0 0
1%
#1245
0%
#1255
1!
b11100001 "
b11100001 2
b1000 ,
b111100000000 .
1%
#1256
b10000 $
b10000 (
b10000 #
b10000 '
#1265
0%
#1275
1%
#1276
b0 -
b0 +
b10000 /
b10000 1
1&
#1285
0%
#1295
0!
b0 ,
b0 *
b10000 .
b10000 0
1%
#1296
b1 -
b100000000 /
b1 1
0&
#1305
0%
#1315
b10 -
b1000000000000 /
b0 1
b100000000 +
b1 )
b1 ,
b100000000 .
b1 0
1%
#1325
0%
#1335
b1000 -
b10000000000000000 /
b0 )
b10 ,
b100000000 *
b1000000000000 .
b0 0
1%
#1345
0%
#1355
1!
b100000000 "
b100000000 2
b1000 ,
b10000000000000000 .
1%
#1356
b10001 $
b10001 (
b10001 #
b10001 '
#1365
0%
#1375
1%
#1376
b0 -
b0 +
b10001 /
b10001 1
1&
#1385
0%
#1395
b1 )
0!
b0 ,
b0 *
b10001 .
b10001 0
1%
#1396
b1 -
b100010000 /
b1 1
b10001 +
0&
#1405
0%
#1415
b10 -
b1000100000000 /
b0 1
b100100001 +
b1 ,
b10001 *
b100010000 .
b1 0
1%
#1425
0%
#1435
b1000 -
b10001000000000000 /
b0 )
b10 ,
b100100001 *
b1000100000000 .
b0 0
1%
#1445
0%
#1455
1!
b100100001 "
b100100001 2
b1000 ,
b10001000000000000 .
1%
#1456
b10010 $
b10010 (
b10010 #
b10010 '
#1465
0%
#1475
1%
#1476
b0 -
b0 +
b10010 /
b10010 1
1&
#1485
0%
#1495
b10 )
0!
b0 ,
b0 *
b10010 .
b10010 0
1%
#1496
b1 -
b100100000 /
b1 1
b100100 +
0&
#1505
0%
#1515
b10 -
b1001000000000 /
b0 1
b101000100 +
b1 )
b1 ,
b100100 *
b100100000 .
b1 0
1%
#1525
0%
#1535
b1000 -
b10010000000000000 /
b0 )
b10 ,
b101000100 *
b1001000000000 .
b0 0
1%
#1545
0%
#1555
1!
b101000100 "
b101000100 2
b1000 ,
b10010000000000000 .
1%
#1556
b10011 $
b10011 (
b10011 #
b10011 '
#1565
0%
#1575
1%
#1576
b0 -
b0 +
b10011 /
b10011 1
1&
#1585
0%
#1595
b11 )
0!
b0 ,
b0 *
b10011 .
b10011 0
1%
#1596
b1 -
b100110000 /
b1 1
b111001 +
0&
#1605
0%
#1615
b10 -
b1001100000000 /
b0 1
b101101001 +
b1 )
b1 ,
b111001 *
b100110000 .
b1 0
1%
#1625
0%
#1635
b1000 -
b10011000000000000 /
b0 )
b10 ,
b101101001 *
b1001100000000 .
b0 0
1%
#1645
0%
#1655
1!
b101101001 "
b101101001 2
b1000 ,
b10011000000000000 .
1%
#1656
b10100 $
b10100 (
b10100 #
b10100 '
#1665
0%
#1675
1%
#1676
b0 -
b0 +
b10100 /
b10100 1
1&
#1685
0%
#1695
b100 )
0!
b0 ,
b0 *
b10100 .
b10100 0
1%
#1696
b1 -
b101000000 /
b1 1
b1010000 +
0&
#1705
0%
#1715
b10 -
b1010000000000 /
b0 1
b110010000 +
b1 )
b1 ,
b1010000 *
b101000000 .
b1 0
1%
#1725
0%
#1735
b1000 -
b10100000000000000 /
b0 )
b10 ,
b110010000 *
b1010000000000 .
b0 0
1%
#1745
0%
#1755
1!
b110010000 "
b110010000 2
b1000 ,
b10100000000000000 .
1%
#1756
b10101 $
b10101 (
b10101 #
b10101 '
#1765
0%
#1775
1%
#1776
b0 -
b0 +
b10101 /
b10101 1
1&
#1785
0%
#1795
b101 )
0!
b0 ,
b0 *
b10101 .
b10101 0
1%
#1796
b1 -
b101010000 /
b1 1
b1101001 +
0&
#1805
0%
#1815
b10 -
b1010100000000 /
b0 1
b110111001 +
b1 )
b1 ,
b1101001 *
b101010000 .
b1 0
1%
#1825
0%
#1835
b1000 -
b10101000000000000 /
b0 )
b10 ,
b110111001 *
b1010100000000 .
b0 0
1%
#1845
0%
#1855
1!
b110111001 "
b110111001 2
b1000 ,
b10101000000000000 .
1%
#1856
b10110 $
b10110 (
b10110 #
b10110 '
#1865
0%
#1875
1%
#1876
b0 -
b0 +
b10110 /
b10110 1
1&
#1885
0%
#1895
b110 )
0!
b0 ,
b0 *
b10110 .
b10110 0
1%
#1896
b1 -
b101100000 /
b1 1
b10000100 +
0&
#1905
0%
#1915
b10 -
b1011000000000 /
b0 1
b111100100 +
b1 )
b1 ,
b10000100 *
b101100000 .
b1 0
1%
#1925
0%
#1935
b1000 -
b10110000000000000 /
b0 )
b10 ,
b111100100 *
b1011000000000 .
b0 0
1%
#1945
0%
#1955
1!
b111100100 "
b111100100 2
b1000 ,
b10110000000000000 .
1%
#1956
b10111 $
b10111 (
b10111 #
b10111 '
#1965
0%
#1975
1%
#1976
b0 -
b0 +
b10111 /
b10111 1
1&
#1985
0%
#1995
b111 )
0!
b0 ,
b0 *
b10111 .
b10111 0
1%
#1996
b1 -
b101110000 /
b1 1
b10100001 +
0&
#2005
0%
#2015
b10 -
b1011100000000 /
b0 1
b1000010001 +
b1 )
b1 ,
b10100001 *
b101110000 .
b1 0
1%
#2025
0%
#2035
b1000 -
b10111000000000000 /
b0 )
b10 ,
b1000010001 *
b1011100000000 .
b0 0
1%
#2045
0%
#2055
1!
b1000010001 "
b1000010001 2
b1000 ,
b10111000000000000 .
1%
#2056
b11000 $
b11000 (
b11000 #
b11000 '
#2065
0%
#2075
1%
#2076
b0 -
b0 +
b11000 /
b11000 1
1&
#2085
0%
#2095
b1000 )
0!
b0 ,
b0 *
b11000 .
b11000 0
1%
#2096
b1 -
b110000000 /
b1 1
b11000000 +
0&
#2105
0%
#2115
b10 -
b1100000000000 /
b0 1
b1001000000 +
b1 )
b1 ,
b11000000 *
b110000000 .
b1 0
1%
#2125
0%
#2135
b1000 -
b11000000000000000 /
b0 )
b10 ,
b1001000000 *
b1100000000000 .
b0 0
1%
#2145
0%
#2155
1!
b1001000000 "
b1001000000 2
b1000 ,
b11000000000000000 .
1%
#2156
b11001 $
b11001 (
b11001 #
b11001 '
#2165
0%
#2175
1%
#2176
b0 -
b0 +
b11001 /
b11001 1
1&
#2185
0%
#2195
b1001 )
0!
b0 ,
b0 *
b11001 .
b11001 0
1%
#2196
b1 -
b110010000 /
b1 1
b11100001 +
0&
#2205
0%
#2215
b10 -
b1100100000000 /
b0 1
b1001110001 +
b1 )
b1 ,
b11100001 *
b110010000 .
b1 0
1%
#2225
0%
#2235
b1000 -
b11001000000000000 /
b0 )
b10 ,
b1001110001 *
b1100100000000 .
b0 0
1%
#2245
0%
#2255
1!
b1001110001 "
b1001110001 2
b1000 ,
b11001000000000000 .
1%
#2256
b11010 $
b11010 (
b11010 #
b11010 '
#2265
0%
#2275
1%
#2276
b0 -
b0 +
b11010 /
b11010 1
1&
#2285
0%
#2295
b1010 )
0!
b0 ,
b0 *
b11010 .
b11010 0
1%
#2296
b1 -
b110100000 /
b1 1
b100000100 +
0&
#2305
0%
#2315
b10 -
b1101000000000 /
b0 1
b1010100100 +
b1 )
b1 ,
b100000100 *
b110100000 .
b1 0
1%
#2325
0%
#2335
b1000 -
b11010000000000000 /
b0 )
b10 ,
b1010100100 *
b1101000000000 .
b0 0
1%
#2345
0%
#2355
1!
b1010100100 "
b1010100100 2
b1000 ,
b11010000000000000 .
1%
#2356
b11011 $
b11011 (
b11011 #
b11011 '
#2365
0%
#2375
1%
#2376
b0 -
b0 +
b11011 /
b11011 1
1&
#2385
0%
#2395
b1011 )
0!
b0 ,
b0 *
b11011 .
b11011 0
1%
#2396
b1 -
b110110000 /
b1 1
b100101001 +
0&
#2405
0%
#2415
b10 -
b1101100000000 /
b0 1
b1011011001 +
b1 )
b1 ,
b100101001 *
b110110000 .
b1 0
1%
#2425
0%
#2435
b1000 -
b11011000000000000 /
b0 )
b10 ,
b1011011001 *
b1101100000000 .
b0 0
1%
#2445
0%
#2455
1!
b1011011001 "
b1011011001 2
b1000 ,
b11011000000000000 .
1%
#2456
b11100 $
b11100 (
b11100 #
b11100 '
#2465
0%
#2475
1%
#2476
b0 -
b0 +
b11100 /
b11100 1
1&
#2485
0%
#2495
b1100 )
0!
b0 ,
b0 *
b11100 .
b11100 0
1%
#2496
b1 -
b111000000 /
b1 1
b101010000 +
0&
#2505
0%
#2515
b10 -
b1110000000000 /
b0 1
b1100010000 +
b1 )
b1 ,
b101010000 *
b111000000 .
b1 0
1%
#2525
0%
#2535
b1000 -
b11100000000000000 /
b0 )
b10 ,
b1100010000 *
b1110000000000 .
b0 0
1%
#2545
0%
#2555
1!
b1100010000 "
b1100010000 2
b1000 ,
b11100000000000000 .
1%
#2556
b11101 $
b11101 (
b11101 #
b11101 '
#2565
0%
#2575
1%
#2576
b0 -
b0 +
b11101 /
b11101 1
1&
#2585
0%
#2595
b1101 )
0!
b0 ,
b0 *
b11101 .
b11101 0
1%
#2596
b1 -
b111010000 /
b1 1
b101111001 +
0&
#2605
0%
#2615
b10 -
b1110100000000 /
b0 1
b1101001001 +
b1 )
b1 ,
b101111001 *
b111010000 .
b1 0
1%
#2625
0%
#2635
b1000 -
b11101000000000000 /
b0 )
b10 ,
b1101001001 *
b1110100000000 .
b0 0
1%
#2645
0%
#2655
1!
b1101001001 "
b1101001001 2
b1000 ,
b11101000000000000 .
1%
#2656
b11110 $
b11110 (
b11110 #
b11110 '
#2665
0%
#2675
1%
#2676
b0 -
b0 +
b11110 /
b11110 1
1&
#2685
0%
#2695
b1110 )
0!
b0 ,
b0 *
b11110 .
b11110 0
1%
#2696
b1 -
b111100000 /
b1 1
b110100100 +
0&
#2705
0%
#2715
b10 -
b1111000000000 /
b0 1
b1110000100 +
b1 )
b1 ,
b110100100 *
b111100000 .
b1 0
1%
#2725
0%
#2735
b1000 -
b11110000000000000 /
b0 )
b10 ,
b1110000100 *
b1111000000000 .
b0 0
1%
#2745
0%
#2755
1!
b1110000100 "
b1110000100 2
b1000 ,
b11110000000000000 .
1%
#2756
b11111 $
b11111 (
b11111 #
b11111 '
#2765
0%
#2775
1%
#2776
b0 -
b0 +
b11111 /
b11111 1
1&
#2785
0%
#2795
b1111 )
0!
b0 ,
b0 *
b11111 .
b11111 0
1%
#2796
b1 -
b111110000 /
b1 1
b111010001 +
0&
#2805
0%
#2815
b10 -
b1111100000000 /
b0 1
b1111000001 +
b1 )
b1 ,
b111010001 *
b111110000 .
b1 0
1%
#2825
0%
#2835
b1000 -
b11111000000000000 /
b0 )
b10 ,
b1111000001 *
b1111100000000 .
b0 0
1%
#2845
0%
#2855
1!
b1111000001 "
b1111000001 2
b1000 ,
b11111000000000000 .
1%
#2856
b100000 $
b100000 (
b100000 #
b100000 '
#2865
0%
#2875
1%
#2876
b0 -
b0 +
b100000 /
b100000 1
1&
#2885
0%
#2895
0!
b0 ,
b0 *
b100000 .
b100000 0
1%
#2896
b1 -
b1000000000 /
b10 1
0&
#2905
0%
#2915
b10 -
b10000000000000 /
b0 1
b10000000000 +
b10 )
b1 ,
b1000000000 .
b10 0
1%
#2925
0%
#2935
b1000 -
b100000000000000000 /
b0 )
b10 ,
b10000000000 *
b10000000000000 .
b0 0
1%
#2945
0%
#2955
1!
b10000000000 "
b10000000000 2
b1000 ,
b100000000000000000 .
1%
#2956
b100001 $
b100001 (
b100001 #
b100001 '
#2965
0%
#2975
1%
#2976
b0 -
b0 +
b100001 /
b100001 1
1&
#2985
0%
#2995
b1 )
0!
b0 ,
b0 *
b100001 .
b100001 0
1%
#2996
b1 -
b1000010000 /
b10 1
b100001 +
0&
#3005
0%
#3015
b10 -
b10000100000000 /
b0 1
b10001000001 +
b10 )
b1 ,
b100001 *
b1000010000 .
b10 0
1%
#3025
0%
#3035
b1000 -
b100001000000000000 /
b0 )
b10 ,
b10001000001 *
b10000100000000 .
b0 0
1%
#3045
0%
#3055
1!
b10001000001 "
b10001000001 2
b1000 ,
b100001000000000000 .
1%
#3056
b100010 $
b100010 (
b100010 #
b100010 '
#3065
0%
#3075
1%
#3076
b0 -
b0 +
b100010 /
b100010 1
1&
#3085
0%
#3095
b10 )
0!
b0 ,
b0 *
b100010 .
b100010 0
1%
#3096
b1 -
b1000100000 /
b10 1
b1000100 +
0&
#3105
0%
#3115
b10 -
b10001000000000 /
b0 1
b10010000100 +
b1 ,
b1000100 *
b1000100000 .
b10 0
1%
#3125
0%
#3135
b1000 -
b100010000000000000 /
b0 )
b10 ,
b10010000100 *
b10001000000000 .
b0 0
1%
#3145
0%
#3155
1!
b10010000100 "
b10010000100 2
b1000 ,
b100010000000000000 .
1%
#3156
b100011 $
b100011 (
b100011 #
b100011 '
#3165
0%
#3175
1%
#3176
b0 -
b0 +
b100011 /
b100011 1
1&
#3185
0%
#3195
b11 )
0!
b0 ,
b0 *
b100011 .
b100011 0
1%
#3196
b1 -
b1000110000 /
b10 1
b1101001 +
0&
#3205
0%
#3215
b10 -
b10001100000000 /
b0 1
b10011001001 +
b10 )
b1 ,
b1101001 *
b1000110000 .
b10 0
1%
#3225
0%
#3235
b1000 -
b100011000000000000 /
b0 )
b10 ,
b10011001001 *
b10001100000000 .
b0 0
1%
#3245
0%
#3255
1!
b10011001001 "
b10011001001 2
b1000 ,
b100011000000000000 .
1%
#3256
b100100 $
b100100 (
b100100 #
b100100 '
#3265
0%
#3275
1%
#3276
b0 -
b0 +
b100100 /
b100100 1
1&
#3285
0%
#3295
b100 )
0!
b0 ,
b0 *
b100100 .
b100100 0
1%
#3296
b1 -
b1001000000 /
b10 1
b10010000 +
0&
#3305
0%
#3315
b10 -
b10010000000000 /
b0 1
b10100010000 +
b10 )
b1 ,
b10010000 *
b1001000000 .
b10 0
1%
#3325
0%
#3335
b1000 -
b100100000000000000 /
b0 )
b10 ,
b10100010000 *
b10010000000000 .
b0 0
1%
#3345
0%
#3355
1!
b10100010000 "
b10100010000 2
b1000 ,
b100100000000000000 .
1%
#3356
b100101 $
b100101 (
b100101 #
b100101 '
#3365
0%
#3375
1%
#3376
b0 -
b0 +
b100101 /
b100101 1
1&
#3385
0%
#3395
b101 )
0!
b0 ,
b0 *
b100101 .
b100101 0
1%
#3396
b1 -
b1001010000 /
b10 1
b10111001 +
0&
#3405
0%
#3415
b10 -
b10010100000000 /
b0 1
b10101011001 +
b10 )
b1 ,
b10111001 *
b1001010000 .
b10 0
1%
#3425
0%
#3435
b1000 -
b100101000000000000 /
b0 )
b10 ,
b10101011001 *
b10010100000000 .
b0 0
1%
#3445
0%
#3455
1!
b10101011001 "
b10101011001 2
b1000 ,
b100101000000000000 .
1%
#3456
b100110 $
b100110 (
b100110 #
b100110 '
#3465
0%
#3475
1%
#3476
b0 -
b0 +
b100110 /
b100110 1
1&
#3485
0%
#3495
b110 )
0!
b0 ,
b0 *
b100110 .
b100110 0
1%
#3496
b1 -
b1001100000 /
b10 1
b11100100 +
0&
#3505
0%
#3515
b10 -
b10011000000000 /
b0 1
b10110100100 +
b10 )
b1 ,
b11100100 *
b1001100000 .
b10 0
1%
#3525
0%
#3535
b1000 -
b100110000000000000 /
b0 )
b10 ,
b10110100100 *
b10011000000000 .
b0 0
1%
#3545
0%
#3555
1!
b10110100100 "
b10110100100 2
b1000 ,
b100110000000000000 .
1%
#3556
b100111 $
b100111 (
b100111 #
b100111 '
#3565
0%
#3575
1%
#3576
b0 -
b0 +
b100111 /
b100111 1
1&
#3585
0%
#3595
b111 )
0!
b0 ,
b0 *
b100111 .
b100111 0
1%
#3596
b1 -
b1001110000 /
b10 1
b100010001 +
0&
#3605
0%
#3615
b10 -
b10011100000000 /
b0 1
b10111110001 +
b10 )
b1 ,
b100010001 *
b1001110000 .
b10 0
1%
#3625
0%
#3635
b1000 -
b100111000000000000 /
b0 )
b10 ,
b10111110001 *
b10011100000000 .
b0 0
1%
#3645
0%
#3655
1!
b10111110001 "
b10111110001 2
b1000 ,
b100111000000000000 .
1%
#3656
b101000 $
b101000 (
b101000 #
b101000 '
#3665
0%
#3675
1%
#3676
b0 -
b0 +
b101000 /
b101000 1
1&
#3685
0%
#3695
b1000 )
0!
b0 ,
b0 *
b101000 .
b101000 0
1%
#3696
b1 -
b1010000000 /
b10 1
b101000000 +
0&
#3705
0%
#3715
b10 -
b10100000000000 /
b0 1
b11001000000 +
b10 )
b1 ,
b101000000 *
b1010000000 .
b10 0
1%
#3725
0%
#3735
b1000 -
b101000000000000000 /
b0 )
b10 ,
b11001000000 *
b10100000000000 .
b0 0
1%
#3745
0%
#3755
1!
b11001000000 "
b11001000000 2
b1000 ,
b101000000000000000 .
1%
#3756
b101001 $
b101001 (
b101001 #
b101001 '
#3765
0%
#3775
1%
#3776
b0 -
b0 +
b101001 /
b101001 1
1&
#3785
0%
#3795
b1001 )
0!
b0 ,
b0 *
b101001 .
b101001 0
1%
#3796
b1 -
b1010010000 /
b10 1
b101110001 +
0&
#3805
0%
#3815
b10 -
b10100100000000 /
b0 1
b11010010001 +
b10 )
b1 ,
b101110001 *
b1010010000 .
b10 0
1%
#3825
0%
#3835
b1000 -
b101001000000000000 /
b0 )
b10 ,
b11010010001 *
b10100100000000 .
b0 0
1%
#3845
0%
#3855
1!
b11010010001 "
b11010010001 2
b1000 ,
b101001000000000000 .
1%
#3856
b101010 $
b101010 (
b101010 #
b101010 '
#3865
0%
#3875
1%
#3876
b0 -
b0 +
b101010 /
b101010 1
1&
#3885
0%
#3895
b1010 )
0!
b0 ,
b0 *
b101010 .
b101010 0
1%
#3896
b1 -
b1010100000 /
b10 1
b110100100 +
0&
#3905
0%
#3915
b10 -
b10101000000000 /
b0 1
b11011100100 +
b10 )
b1 ,
b110100100 *
b1010100000 .
b10 0
1%
#3925
0%
#3935
b1000 -
b101010000000000000 /
b0 )
b10 ,
b11011100100 *
b10101000000000 .
b0 0
1%
#3945
0%
#3955
1!
b11011100100 "
b11011100100 2
b1000 ,
b101010000000000000 .
1%
#3956
b101011 $
b101011 (
b101011 #
b101011 '
#3965
0%
#3975
1%
#3976
b0 -
b0 +
b101011 /
b101011 1
1&
#3985
0%
#3995
b1011 )
0!
b0 ,
b0 *
b101011 .
b101011 0
1%
#3996
b1 -
b1010110000 /
b10 1
b111011001 +
0&
#4005
0%
#4015
b10 -
b10101100000000 /
b0 1
b11100111001 +
b10 )
b1 ,
b111011001 *
b1010110000 .
b10 0
1%
#4025
0%
#4035
b1000 -
b101011000000000000 /
b0 )
b10 ,
b11100111001 *
b10101100000000 .
b0 0
1%
#4045
0%
#4055
1!
b11100111001 "
b11100111001 2
b1000 ,
b101011000000000000 .
1%
#4056
b101100 $
b101100 (
b101100 #
b101100 '
#4065
0%
#4075
1%
#4076
b0 -
b0 +
b101100 /
b101100 1
1&
#4085
0%
#4095
b1100 )
0!
b0 ,
b0 *
b101100 .
b101100 0
1%
#4096
b1 -
b1011000000 /
b10 1
b1000010000 +
0&
#4105
0%
#4115
b10 -
b10110000000000 /
b0 1
b11110010000 +
b10 )
b1 ,
b1000010000 *
b1011000000 .
b10 0
1%
#4125
0%
