exercises/e9_fsm/fsm.v
module fsm(
    input logic clk,
    input logic reset,
    input logic sample_valid,
    input logic[2:0] sample_value,
    output logic[7:0] sum,
    output logic[7:0] count
);

    logic[7:0] sum_curr;
    logic[7:0] count_curr;

    always @(*) begin
        if (reset) begin
            sum_curr = 0;
            count_curr = 0;
        end
        else if (sample_valid) begin
            sum_curr = sum_curr + sample_value;
            count_curr++;
        end
    end

    always_ff @(posedge clk) begin
        sum <= sum_curr;
        count <= count_curr;
    end

endmodule

exercises/e9_fsm/fsm_tb.v
module fsm_tb();
    logic clk;
    initial begin
        $dumpfile("fsm_tb.vcd");
        $dumpvars(0, fsm_tb);
        clk = 0;
        repeat (20) begin
            #4;
            clk = !clk;
        end
        $finish(0);
    end

    logic reset, sample_valid;
    logic[2:0] sample_value;
    logic[7:0] sum, count;
    initial begin
        reset = 1;
        sample_valid = 0;
        sample_value = 1;
        @(posedge clk);
        #1;
        $display("sum: %d count:%d", sum, count);
        assert(sum == 0 && count == 0);

        reset = 0;
        sample_valid = 1;
        @(posedge clk);
        #1;
        $display("sum: %d count:%d", sum, count);
        assert(sum == 1 && count == 1);

        sample_valid = 0;
        sample_value = 2;
        @(posedge clk);
        #1;
        $display("sum: %d count:%d", sum, count);
        assert(sum == 1 && count == 1);

        sample_valid = 1;
        sample_value = 3;
        @(posedge clk);
        #1;
        $display("sum: %d count:%d", sum, count);
        assert(sum == 4 && count == 2);

        sample_valid = 0;
        sample_value = 3;
        @(posedge clk);
        #1;
        $display("sum: %d count:%d", sum, count);
        assert(sum == 4 && count == 2);

        reset = 1;
        @(posedge clk);
        #1;
        $display("sum: %d count:%d", sum, count);
        assert(sum == 0 && count == 0);


    end

    fsm dut(
        .clk(clk), .reset(reset), .sample_valid(sample_valid),
        .sample_value(sample_value),
        .sum(sum),
        .count(count)
    );

endmodule

exercises/e9_fsm/fsm_tb.vcd
$date
	Wed Nov 10 17:57:45 2021
$end
$version
	Icarus Verilog
$end
$timescale
	1s
$end
$scope module fsm_tb $end
$var wire 8 ! sum [7:0] $end
$var wire 8 " count [7:0] $end
$var reg 1 # clk $end
$var reg 1 $ reset $end
$var reg 1 % sample_valid $end
$var reg 3 & sample_value [2:0] $end
$scope module dut $end
$var wire 1 # clk $end
$var wire 1 $ reset $end
$var wire 1 % sample_valid $end
$var wire 3 ' sample_value [2:0] $end
$var reg 8 ( count [7:0] $end
$var reg 8 ) count_curr [7:0] $end
$var reg 8 * sum [7:0] $end
$var reg 8 + sum_curr [7:0] $end
$upscope $end
$upscope $end
$enddefinitions $end
#0
$dumpvars
b0 +
bx *
b0 )
bx (
b1 '
b1 &
0%
1$
0#
bx "
bx !
$end
#4
b0 "
b0 (
b0 !
b0 *
1#
#5
b1 )
b1 +
1%
0$
#8
0#
#12
b1 "
b1 (
b1 !
b1 *
1#
#13
b10 &
b10 '
0%
#16
0#
#20
1#
#21
b10 )
b100 +
b11 &
b11 '
1%
#24
0#
#28
b10 "
b10 (
b100 !
b100 *
1#
#29
0%
#32
0#
#36
1#
#37
b0 )
b0 +
1$
#40
0#
#44
b0 "
b0 (
b0 !
b0 *
1#
